fast_gmail/__init__.py
fast_gmail/draft.py
fast_gmail/gmail.py
fast_gmail/helpers.py
fast_gmail/message.py
fast_gmail/search.py
fast_gmail-1.3.0.dist-info/LICENSE
fast_gmail-1.3.0.dist-info/METADATA
fast_gmail-1.3.0.dist-info/WHEEL
fast_gmail-1.3.0.dist-info/top_level.txt
fast_gmail-1.3.0.dist-info/RECORD
